Metadata-Version: 2.1
Name: refex
Version: 0.1.1
Summary: A syntactically-aware search and replace tool.
License: Apache-2.0
Author: Devin Jeanpierre
Author-email: jeanpierreda@gmail.com
Requires-Python: >=3.6,<4.0
Classifier: Development Status :: 3 - Alpha
Classifier: Environment :: Console
Classifier: Intended Audience :: Developers
Classifier: License :: OSI Approved :: Apache Software License
Classifier: Operating System :: POSIX
Classifier: Programming Language :: Python :: 3
Classifier: Programming Language :: Python :: 3.6
Classifier: Programming Language :: Python :: 3.7
Classifier: Programming Language :: Python :: 3.8
Classifier: Programming Language :: Python :: 3.9
Classifier: Topic :: Software Development
Classifier: Topic :: Software Development :: Libraries :: Python Modules
Provides-Extra: docs
Requires-Dist: absl-py (>=0.9,<0.10)
Requires-Dist: asttokens (>=2,<3)
Requires-Dist: attrs (>=19.2,<20.0)
Requires-Dist: cached-property (>=1,<2)
Requires-Dist: colorama (>=0.4,<0.5)
Requires-Dist: m2r (>=0.2,<0.3); extra == "docs"
Requires-Dist: six
Requires-Dist: sphinx (>=2.4,<3.0); extra == "docs"
